odoo9_addon_mass_mailing_security_group-9.0.1.0.0-py2.7-nspkg.pth
odoo_addons/mass_mailing_security_group/__openerp__.py
odoo_addons/mass_mailing_security_group/__init__.py
odoo_addons/mass_mailing_security_group/README.rst
odoo_addons/mass_mailing_security_group/security/mail_mass_mailing_security.xml
odoo_addons/mass_mailing_security_group/security/ir.model.access.csv
odoo_addons/mass_mailing_security_group/i18n/es.po
odoo_addons/mass_mailing_security_group/i18n/sl.po
odoo_addons/mass_mailing_security_group/i18n/de.po
odoo_addons/mass_mailing_security_group/i18n/fr.po
odoo_addons/mass_mailing_security_group/wizards/test_mailing.py
odoo_addons/mass_mailing_security_group/wizards/__init__.py
odoo_addons/mass_mailing_security_group/static/description/icon.png
odoo9_addon_mass_mailing_security_group-9.0.1.0.0.dist-info/top_level.txt
odoo9_addon_mass_mailing_security_group-9.0.1.0.0.dist-info/WHEEL
odoo9_addon_mass_mailing_security_group-9.0.1.0.0.dist-info/RECORD
odoo9_addon_mass_mailing_security_group-9.0.1.0.0.dist-info/metadata.json
odoo9_addon_mass_mailing_security_group-9.0.1.0.0.dist-info/DESCRIPTION.rst
odoo9_addon_mass_mailing_security_group-9.0.1.0.0.dist-info/METADATA
odoo9_addon_mass_mailing_security_group-9.0.1.0.0.dist-info/namespace_packages.txt
